CHANGELOG.md
pycounts_gaurav/__init__.py
pycounts_gaurav/data/__init__.py
pycounts_gaurav/data/flatland.txt
pycounts_gaurav/datasets.py
pycounts_gaurav/plotting.py
pycounts_gaurav/pycounts_gaurav.py
pycounts_gaurav-0.5.0.dist-info/LICENSE
pycounts_gaurav-0.5.0.dist-info/METADATA
pycounts_gaurav-0.5.0.dist-info/WHEEL
pycounts_gaurav-0.5.0.dist-info/RECORD
