Metadata-Version: 2.1
Name: pycounts_gaurav
Version: 0.5.0
Summary: counts word counts in a text file
License: MIT
Author: Gaurav Parajuli
Requires-Python: >=3.9
Classifier: License :: OSI Approved :: MIT License
Classifier: Programming Language :: Python :: 3
Classifier: Programming Language :: Python :: 3.9
Classifier: Programming Language :: Python :: 3.10
Classifier: Programming Language :: Python :: 3.11
Classifier: Programming Language :: Python :: 3.12
Requires-Dist: matplotlib (>=3.9.2)
